pyaxe_flask/__init__.py
pyaxe_flask/frequest.py
pyaxe_flask-2020.8.19.dist-info/LICENSE
pyaxe_flask-2020.8.19.dist-info/METADATA
pyaxe_flask-2020.8.19.dist-info/WHEEL
pyaxe_flask-2020.8.19.dist-info/top_level.txt
pyaxe_flask-2020.8.19.dist-info/RECORD
